LICENSE
MANIFEST.in
README.rst
setup.py
django_model_revision.egg-info/PKG-INFO
django_model_revision.egg-info/SOURCES.txt
django_model_revision.egg-info/dependency_links.txt
django_model_revision.egg-info/not-zip-safe
django_model_revision.egg-info/requires.txt
django_model_revision.egg-info/top_level.txt
model_revision/__init__.py
model_revision/admin.py
model_revision/apps.py
model_revision/decorators.py
model_revision/models.py
model_revision/signals.py
model_revision/views.py
model_revision/migrations/0001_initial.py
model_revision/migrations/__init__.py