Metadata-Version: 1.1
Name: django-model-revision
Version: 0.0.5
Summary: A Django app.
Home-page: UNKNOWN
Author: Moritz Pfeiffer
Author-email: moritz.pfeiffer@alp-phone.ch
License: Other/Proprietary License
Platform: UNKNOWN
Classifier: Development Status :: 5 - Production/Stable
Classifier: Environment :: Web Environment
Classifier: Framework :: Django
Classifier: Intended Audience :: Developers
Classifier: License :: Other/Proprietary License
Classifier: Operating System :: OS Independent
Classifier: Programming Language :: Python
Classifier: Programming Language :: Python :: 3.4
Classifier: Topic :: Internet :: WWW/HTTP
Classifier: Topic :: Internet :: WWW/HTTP :: Dynamic Content
